Workbook

Sheet Transaction Comps
B2: Name | C2: Valuation | D2: Revenue | E2: EV/ Revenue | F2: Acquiror | G2: Acquisition Date | H2: Last Funding Round/Raise/pre-money Valuation | I2: Industry Segment
B3: Zingle | C3: 47.3 | D3: NA | E3: NA | F3: Medallia | G3: 43709 | H3: Series B/$11mm/$16mm | I3: Consumer Engagement
B4: Smooch | C4: 71.9 | D4: NA | E4: NA | F4: Zendesk | G4: 43586 | H4: Seed/$10mm | I4: Consumer Engagement
B5: Outbound | C5: 16.56 | D5: NA | E5: NA | F5: Salesforce Ventures | G5: 42826 | H5: Seed/$2mm | I5: Consumer Engagement
B6: Jirafe | C6: NA | D6: NA | E6: NA | F6: SAP | G6: 42522 | H6: Series A/$6.8M/12mm | I6: Ecommerce Analytics
B7: Zappos | C7: 1134 | F7: Amazon | G7: 40118 | H7: Series G/$90M | I7: Ecommerce/Retail
B8: Bonobos | C8: 310 | F8: Walmart | G8: 42887 | H8: Series D/$55M/$244 | I8: Ecommerce/Retail
B9: Jet | C9: 3200 | F9: Walmart | G9: 42614 | H9: Series B/$350/$1.05B | I9: Ecommerce
B10: Dollar Shave Club | C10: 1000 | F10: Unilever | G10: 42583 | H10: Series D/$90M/$539 | I10: Ecommerce/Retail
B11: Upstream Commerce | C11: NA | F11: Flipkart | G11: 43344 | H11: Series A/$6.25M | I11: Ecommerce Analytics
B12: Honey | C12: 4000 | F12: Paypal | G12: 43831 | H12: Series C/$26M | I12: Ecommerce
B14: Median | C14: =MEDIAN(C3:C12) -> 655 | D14: NA | E14: NA
B15: Average | C15: =AVERAGE(C3:C12) -> 1222.47 | D15: NA | E15: NA

Sheet Public Comps
B2: Name | C2: Revenue | D2: EBITDA | E2: Market Cap | F2: Enterprise Value | G2: EBIDTA Margin | H2: YOY Growth | I2: EV/Rev | J2: Industry Segment
B3: Medallia | C3: 524.487 | D3: -142.695 | E3: 5455 | F3: 5570 | G3: -0.191 | H3: 0.56 | I3: 10.62 | J3: Customer Engagement and Service
B4: HubSpot | C4: 1072.604 | D4: -9.605 | E4: 34047 | F4: 32260 | G4: 0.0121 | H4: 0.28 | I4: 30.08 | J4: Customer Engagement and Service
B5: Zendesk | C5: 1161.688 | D5: -114.211 | E5: 14960 | F5: 15200 | G5: -0.15 | H5: 0.36 | I5: 13.09 | J5: Customer Engagement and Service
B6: Zuora | C6: 323.349 | D6: -58.409 | E6: 2090 | F6: 1950 | G6: -0.23 | H6: 0.17 | I6: 6.04 | J6: Subscription Management
B7: Salesforce | C7: 23539 | D7: 4046 | E7: 255060 | F7: 260930 | G7: 0.1662 | H7: 0.2873 | I7: 11.08 | J7: Customer Relationship Management
B8: Target | C8: 100328 | D8: 11497 | E8: 120380 | F8: 128260 | G8: 0.0931 | H8: 0.0366 | I8: 1.28 | J8: Retail
B9: Walmart | C9: 566145 | D9: 29327 | E9: 403580 | F9: 441630 | G9: 0.064 | H9: 0.0186 | I9: 0.78 | J9: Retail
B10: Shopify | C10: 3853.241 | D10: 266203 | E10: 184940 | F10: 178270 | G10: -0.0687 | H10: 0.47 | I10: =26.26 -> 26.26 | J10: Ecommerce
B11: Etsy | C11: 818 | D11: 139 | E11: 5249 | F11: 5265 | G11: 0.1708 | H11: 0.355 | I11: 7.03 | J11: Ecommerce
B13: Total Median | C13: =MEDIAN(C3:C11) -> 1161.688 | D13: =MEDIAN(D3:D11) -> 139 | E13: =MEDIAN(E3:E11) -> 34047 | F13: =MEDIAN(F3:F11) -> 32260 | G13: =MEDIAN(G3:G11) -> 0.0121 | H13: =MEDIAN(H3:H11) -> 0.2873 | I13: =MEDIAN(I3:I11) -> 10.62
B14: Total Average | C14: =AVERAGE(C3:C11) -> 77529.485 | D14: =AVERAGE(D3:D11) -> 34543.009 | E14: =AVERAGE(E3:E11) -> 113973.44 | F14: =AVERAGE(F3:F11) -> 118815 | G14: =AVERAGE(G3:G11) -> -0.014833333 | H14: =AVERAGE(H3:H11) -> 0.28194444 | I14: =AVERAGE(I3:I11) -> 11.806667
B18: Unused Comps | J18: R
B19: Alteryx | C19: 417 | D19: 36 | E19: 6512 | F19: 6358 | G19: 0.09 | H19: 0.64 | I19: 17.1 | J19: Data Analytics
B20: Domo | C20: 173 | D20: -117 | E20: 674 | F20: 659 | G20: -0.68 | H20: 0.22 | I20: 3.96 | J20: Data Analytics

Sheet Private Comps
B2: Name | C2: Revenue | D2: Total Raised | E2: Latest Stage | F2: Latest Valuation ($mm) | G2: Notable Investors | H2: Industry Segment
B3: Replenium | C3: NA | D3: 18 | E3: Series A | F3: NA | G3: GLP, Consumer Equity Partners | H3: Replenishment Software
B4: OrderGroove | C4: NA | D4: 41 | E4: Series C | F4: NA | G4: SWaN & Legend, SVB, Lerer Hippeau, | H4: Replenishment Software
B5: Kwik | C5: NA | D5: 3 | E5: Seed | F5: NA | G5: Alpana Ventures, Ataria Ventures, Norwest Venture Partners, Charmides Capital | H5: Replenishment Software
B6: SmartCommerce | C6: NA | D6: 8 | E6: Series A | F6: 16 | G6: Bright Capital, Edemic Capital, Run Capital, Valor Ventures | H6: Replenishment Software
B7: Recurly | C7: NA | D7: 42 | E7: Series C | F7: NA | G7: SVB, F-Prime Ventures, Greycroft, 500 Startups | H7: Subscription Management
B8: ChargeBee | C8: NA | D8: 38 | E8: Series D | F8: 145 | G8: Insight Partners, Tiger Global, Accel | H8: Subscription Management
B9: LeanPlum | C9: NA | D9: 145 | E9: Series D1 | F9: 114 | G9: Calterra Capital, Norwest Venture Partners, Canaan Partners, Kleiner Perkins, Shasta Ventures | H9: Marketing Software and Analytics
B10: Attentive | C10: NA | D10: 163 | E10: Series C | F10: 300 | G10: Sequoia Capital, IVP, Bain Capital, Eniac Ventures | H10: Consumer Engagement and Communication Tools
B11: Airship | C11: NA | D11: 100 | E11: Series F | F11: 165 | G11: True Ventures, Foundry Group, QuestMark Partners, Verizon Ventures | H11: Consumer Engagement and Communication Tools
B12: BigCommerce | D12: 228 | E12: Series F | F12: 450 | G12: Goldman Sachs, General Catalyst, GGV | H12: Ecommerce Platform
B14: Median | D14: =MEDIAN(D3:D12) -> 41.5 | F14: =MEDIAN(F3:F11) -> 145
B15: Average | D15: =AVERAGE(D3:D12) -> 78.6 | F15: =AVERAGE(F3:F11) -> 148

Sheet Private Comps Descriptions
B1: Name | C1: Description | D1: Notable Investors
B2: ='Private Comps'!B3 -> Replenium | C2: Developer of an identity verification system designed to check frauds and make identity management effective and simple for banks and financial institutions. | D2: ='Private Comps'!G3 -> GLP, Consumer Equity Partners
A3: - | B3: ='Private Comps'!B4 -> OrderGroove | C3: The company's machine learning platform applies machine learning technology to large data sets to detect anomalies and highlight potential cases of fraud associated with banking and shopping, enabling users to prevent fraud. | D3: ='Private Comps'!G4 -> SWaN & Legend, SVB, Lerer Hippeau,
B4: ='Private Comps'!B5 -> Kwik | C4: Information technology company that focuses on financial services and provides fraud prevention, anti-spam, and abuse analysis for businesses, companies, and industries. Its technology is designed for retail, gaming, and fintech | D4: ='Private Comps'!G5 -> Alpana Ventures, Ataria Ventures, Norwest Venture Partners, Charmides Capital
B5: ='Private Comps'!B6 -> SmartCommerce | C5: Security analysis software designed to offer big data fraud detection solutions at a massive scale. The company's security analysis software utilizes unsupervised analytics to identify malicious account campaigns before conducting any damage to banks, consumer-facing web sites and mobile applications | D5: ='Private Comps'!G6 -> Bright Capital, Edemic Capital, Run Capital, Valor Ventures
B6: ='Private Comps'!B7 -> Recurly | C6: Provides a risk management tool for online fraud detection, forensics and ongoing risk monitoring to financial institutions such as banks, credit unions and brokerage companies, enabling users to protect their privacy. | D6: ='Private Comps'!G7 -> SVB, F-Prime Ventures, Greycroft, 500 Startups
B7: ='Private Comps'!B8 -> ChargeBee | C7: Platform provides real-time insights into the risk of companies globally and changes how companies assess who they're doing business with, while automating compliance and risk processes, enabling firms make intelligent risk decisions faster. | D7: ='Private Comps'!G8 -> Insight Partners, Tiger Global, Accel
B8: ='Private Comps'!B9 -> LeanPlum | C8: Developer of cloud-based fraud detection and anti-money laundering software designed to identify entities that may be involved in money laundering or terrorist financing activities. Big Data/machine learning offerings analyze deposit, check, card, ACH and wire frauds, among others. | D8: ='Private Comps'!G9 -> Calterra Capital, Norwest Venture Partners, Canaan Partners, Kleiner Perkins, Shasta Ventures

Sheet Competitive Landscape Map
C2: Digital Adoption and Enablement | F2: Knowledge Management | G2: Communication | I2: Product Creation
C3: Minerva | D3: Spekit | E3: WalkMe | F3: Guru | G3: Loom | H3: CloudApp | I3: Pendo | J3: UserPilot
B4: Video | G4: x | H4: x
B5: Focus on Customer Support Use Cases | C5: x | E5: x | F5: x | G5: x | H5: x
B6: Focus on Sales, L&D | D6: x | E6: x | F6: x
B7: Pricing | C7: $0 Basic $10 Enterprises $12 Premium Individuals | D7: $10 starter | E7: Enterprise | F7: $0 Starter $14 Builder $24 Expert | G7: $0 basic $10 Pro $15 Business | H7: $0 basic $9 Pro $8 Business | I7: Enterprise | J7: Enterprise
B8: Desktop | E8: x | G8: x | H8: x
B9: Chrome extension | C9: x | D9: x | E9: x | F9: x | G9: x | H9: x | J9: x
B10: No code | C10: x | D10: x | G10: x | H10: x | I10: x | J10: x
B11: Data accessible across all websites | C11: x | D11: x | F11: x
B12: Guided workflows | C12: x | D12: x

Sheet Potential Acquirers
B1: Company | C1: Description | D1: Opportunity/Impact
B2: Intuit | C2: Intuit provides financial software products such as TurboTax, QuickBooks, Mint.com and Credit Karma for individuals and small businesses in the areas of tax, accounting, and credit score management. QuickBooks Capital was launched in 2017 to provide loans to small businesses. | D2: Intuit can improve its existing capabilities in credit score improvement and access to credit by adding the analytics and user interface that Curu offers
A3: - | B3: Oracle | C3: Oracle is a large software provider to the banking industry. Within retail banking, its services allow banks to create new products and develop new channels for customer interaction. | D3: Oracle can expand its retail banking offerings and help its clients manage tightening credit standards while better serving consumers
B4: SAP | C4: SAP is a large software provider to the banking industry, with product offerings including spend management and a platform to reach underbanked customers. | D4: SAP can improve its product offerings to help its banking clients save on customer acquisition costs and support financial inclusion
B5: FIS | C5: FIS is a financial software provider with offerings in banking, merchandising and capital markets. FIS is an investor in Curu. | D5: FIS can help its clients be more competitive in the lending market, including by helping its community banking and credit union clients modernize

Sheet Sheet1
