Workbook
Name acqDemoConversionRate: '[1]Customer Acquisition Detail'!$B$15
Name ACV: [1]Assumptions!#REF!
Name AverageContractValue: [1]Assumptions!#REF!
Name AWSCostPerCustomer: '[1]Cost Detail'!$C$6
Name begCustomerAcquisitions: '[1]Customer Acquisition Detail'!#REF!
Name benefitsLoad: '[1]Cost Detail'!$C$33
Name benefitsRate: [2]Controls!$B$12
Name bhb: [1]Assumptions!#REF!
Name BookedDemoConversionRate: '[1]Customer Acquisition Detail'!$B$8
Name bubbleMainAppSubscription: '[1]Cost Detail'!$C$7
Name bubbleSubAppSubscription: '[1]Cost Detail'!$C$8
Name CommunityMemberGrowthRate: '[1]Customer Acquisition Detail'!$C$13
Name ContentMarketingSpendGrowthRate: '[1]Cost Detail'!$D$30
Name customerAcqMonthlyGrowthRate: '[1]Customer Acquisition Detail'!#REF!
Name demoCloseConversionRate: '[1]Customer Acquisition Detail'!$B$17
Name employeeOnboardingCost: '[1]Cost Detail'!$C$34
Name employeeTechCost: '[1]Cost Detail'!#REF!
Name EventRegistrationsRepeatAcqRate: '[1]Customer Acquisition Detail'!$E$12
Name monthlyContentMarketingSpend: '[1]Cost Detail'!$C$30
Name monthlyERGevents: '[1]Cost Detail'!$C$29
Name monthlyLegalCounsel: '[1]Cost Detail'!$C$26
Name monthlyLegalFees: '[1]Cost Detail'!#REF!
Name OrganicTrafficRepeatAcqRate: '[1]Customer Acquisition Detail'!$E$7
Name seedFinanceAmount: [1]Assumptions!$B$11
Name Software1000seats: [1]Assumptions!#REF!
Name Software2000seats: [1]Assumptions!#REF!
Name Software250seats: [1]Assumptions!#REF!
Name Software3000seats: [1]Assumptions!#REF!
Name Software500seats: [1]Assumptions!#REF!
Name SoftwareEnterprise: [1]Assumptions!#REF!
Name StartDate: [2]Controls!$B$6
Name subActiveCampaign: '[1]Cost Detail'!#REF!
Name subGSuite: '[1]Cost Detail'!$C$23
Name TemplateDownloadRepeatAcqRate2: '[1]Customer Acquisition Detail'!$E$11
Name tt: [3]Cover!$C$6
Name year1ACV: [1]Assumptions!$B$3
Name year2ACV: [1]Assumptions!$B$4
Name year3ACV: [1]Assumptions!$B$5
Name TrainingCostPerEmployee: #REF!
Name SPR01B_18: #REF!
Name LItoUserConversion: #REF!
Name AverageARDays: #REF!
Name TrainingPerEmployeePerMonth: #REF!
Name CPCGoogle: #REF!
Name eCommerceMargin: #REF!
Name AverageCPConFACEBOOK: #REF!
Name AvgCPConLinkedIn: #REF!
Name SEMToEcommerce: #REF!
Name DirectTrafficMultiplier: #REF!
Name OpeningCashBalance: #REF!
Name LegalAndAccountingMonthly: #REF!
Name MarketingPercentofMRR: #REF!
Name UserToPremiumTrialConversion: #REF!
Name OrganicToSubscriberConversion: #REF!
Name InsuranceBenefitsMultiplier: #REF!
Name SPR01C_18: #REF!
Name SPR01A_18: #REF!
Name FBtoSubscriberConversion: #REF!
Name VIsitsPerFBPicturePost: #REF!
Name OrdersPerWarehouseHelpPerson: #REF!

Sheet TAM
B4: Market Sizing
B6: Physician Matching Product
B7: # of physicians in the US | C7: 1109460 | D7: Source
B8: Practice size | C8: % of physicians | D8: # of physicians* | E8: est. volume | F8: ACV
B9: 0-10 physicians | C9: =0.328+0.19 -> 0.518 | D9: =$C$7*C9 -> 574700.28 | E9: =D9/5 -> 114940.06 | F9: 20000 | G9: Source
B10: 11-49 physicians | C10: =0.121+0.077 -> 0.198 | D10: =$C$7*C10 -> 219673.08 | E10: =D10/30 -> 7322.436 | F10: 20000 | G10: Source
B11: 50+ physicians | C11: 0.183 | D11: =$C$7*C11 -> 203031.18 | E11: =D11/70 -> 2900.4454 | F11: 20000 | G11: Source
B12: Hospitals | C12: 0.1 | D12: =$C$7*C12 -> 110946 | E12: 6129 | F12: 20000
B13: Total Rev. Oppty. - Physician Matching Product | F13: =SUMPRODUCT(E9:E12,F9:F12) -> 2625838749
B15: *based on 1.1M physicians in the US
B16: Source: American Medical Association
B18: Revenue Expansion Opportunities
B19: Expansion Opportunity | F19: ACV Lift
B20: Applicant Tracking System | F20: 5000 | G20: HCP assumptions
B21: Role expansion (e.g., PA, NP) | F21: 10000 | G21: HCP assumptions
B22: Payroll | F22: 10000 | G22: HCP assumptions
B23: Total Rev. Expansion Oppty. | F23: =SUM(F20:F22)*SUM(E9:E12) -> 3282298436
B25: TAM | F25: =F13+F23 -> 5908137184
B26: HCP Market Penetration Assumption | F26: 0.02
B27: Accel Health Revenue Opportunity | F27: =F25*F26 -> 1.1816274e+08

Sheet 2 year rev build
B2: Assumptions / inputs
B3: Total potential customers | C3: =SUM(TAM!E9:E12) -> 131291.94 | D3: TAM
B4: Run-rate ACV | C4: 20000 | D4: Mgmt
B6: 2 Year Revenue Build | C6: 1Q25E | D6: 2Q25 | E6: 3Q25 | F6: 4Q25 | G6: 1Q26 | H6: 2Q26 | I6: 3Q26 | J6: 4Q26 | K6: 1Q27
B7: Total customers | C7: 30 | D7: 40 | E7: 50 | F7: 65 | G7: 80 | H7: 95 | I7: 110 | J7: 130 | K7: 150
B8: Implied penetration of customers | C8: =(C7)/$C$3 -> 0.00022849842 | D8: =(D7)/$C$3 -> 0.00030466456 | E8: =(E7)/$C$3 -> 0.0003808307 | F8: =(F7)/$C$3 -> 0.00049507991 | G8: =(G7)/$C$3 -> 0.00060932911 | H8: =(H7)/$C$3 -> 0.00072357832 | I8: =(I7)/$C$3 -> 0.00083782753 | J8: =(J7)/$C$3 -> 0.00099015981 | K8: =(K7)/$C$3 -> 0.0011424921
B9: ACV | C9: 18000 | D9: 18000 | E9: 18500 | F9: 18500 | G9: 19000 | H9: 19000 | I9: =$C$4 -> 20000 | J9: =$C$4 -> 20000 | K9: =$C$4 -> 20000
B10: ARR | C10: =C7*C9 -> 540000 | D10: =D7*D9 -> 720000 | E10: =E7*E9 -> 925000 | F10: =F7*F9 -> 1202500 | G10: =G7*G9 -> 1520000 | H10: =H7*H9 -> 1805000 | I10: =I7*I9 -> 2200000 | J10: =J7*J9 -> 2600000 | K10: =K7*K9 -> 3000000
B11: ARR growth | D11: =(D10-C10)/C10 -> 0.33333333 | E11: =(E10-D10)/D10 -> 0.28472222 | F11: =(F10-E10)/E10 -> 0.3 | G11: =(G10-F10)/F10 -> 0.26403326 | H11: =(H10-G10)/G10 -> 0.1875 | I11: =(I10-H10)/H10 -> 0.21883657 | J11: =(J10-I10)/I10 -> 0.18181818 | K11: =(K10-J10)/J10 -> 0.15384615

Sheet Exit Scenario
B4: Exit Assumptions | C4: Seed | D4: Series A | E4: Series B | F4: Series C | G4: Total
B5: Post-money Valuation | C5: 25 | D5: 50 | E5: 100 | F5: 250
B6: Raise | C6: 4 | D6: 10 | E6: 15 | F6: 25 | G6: =SUM(C6:F6) -> 54
B7: Ownership | C7: =C6/C5 -> 0.16 | D7: =D6/D5 -> 0.2 | E7: =E6/E5 -> 0.15 | F7: =F6/F5 -> 0.1
B8: HCP Allocation | C8: 2.5 | D8: =C10*D6 -> 1 | E8: 0 | F8: 0 | G8: =SUM(C8:F8) -> 3.5
B9: Post Money Options | C9: 0.07 | D9: 0.07 | E9: 0 | F9: 0
B10: HCP Round Ownership | C10: =C8/C5 -> 0.1 | D10: =D8/D5 -> 0.02 | E10: =E8/E5 -> 0 | F10: =F8/F5 -> 0
B11: Total HCP Ownership | D11: =D10+C10*(1-D7-D9) -> 0.093 | E11: =E10+D11*(1-E7-E9) -> 0.07905 | F11: =F10+E11*(1-F7-F9) -> 0.071145
B15: 2031 Exit Scenario | C15: =C4 -> Seed | D15: =D4 -> Series A | E15: =E4 -> Series B | F15: =F4 -> Series C | G15: =G4 -> Total
B16: Exit Revenue (HCP est.) | G16: 269.1
B17: Exit Multiple | G17: 7
B18: Exit Purchase Price | C18: =D18 -> 1883.7 | D18: =E18 -> 1883.7 | E18: =F18 -> 1883.7 | F18: =G18 -> 1883.7 | G18: =G17*G16 -> 1883.7
B19: Exit Ownership | C19: =C10*(1-$D$7-$D$9)*(1-$E$7-$E$9)*(1-$F$7-$F$9) -> 0.055845 | D19: =D10*(1-$E$7-$E$9)*(1-$F$7-$F$9) -> 0.0153 | E19: =E10*(1-$F$7-$F$9) -> 0 | F19: =F10*85%*90% -> 0 | G19: =SUM(C19:F19) -> 0.071145
B20: HCP Return | C20: =C18*C19 -> 105.19523 | D20: =D18*D19 -> 28.82061 | E20: =E18*E19 -> 0 | F20: =F18*F19 -> 0 | G20: =G19*G18 -> 134.01584
B21: HCP MOIC | C21: =IFERROR(C20/C8,"-") -> 42.078091 | D21: =IFERROR(D20/D8,"-") -> 28.82061 | E21: =IFERROR(E20/E8,"-") -> - | F21: =IFERROR(F20/F8,"-") -> - | G21: =G20/G8 -> 38.290239
K22: HCP Return
B23: Dilution | C23: =IFERROR(1-C19/C10,"-") -> 0.44155 | D23: =IFERROR(1-D19/D10,"-") -> 0.235 | E23: =IFERROR(1-E19/E10,"-") -> - | F23: =IFERROR(1-F19/F10,"-") -> - | G23: =1-G19/SUM(C10:F10) -> 0.407125 | K23: Exit Valuation
J24: =$G$20 -> 134.01584 | K24: 1600 | L24: 1700 | M24: 1883.7 | N24: 2000 | O24: 2100
I25: Initial Check | J25: 2 | K25: 91.0656 | L25: 96.7572 | M25: 107.21267 | N25: 113.832 | O25: 119.5236
J26: 2.2 | K26: 100.17216 | L26: 106.43292 | M26: 117.93394 | N26: 125.2152 | O26: 131.47596
J27: 2.5 | K27: 113.832 | L27: 120.9465 | M27: 134.01584 | N27: 142.29 | O27: 149.4045
J28: 2.6 | K28: 118.38528 | L28: 125.78436 | M28: 139.37647 | N28: 147.9816 | O28: 155.38068
J29: 2.7 | K29: 122.93856 | L29: 130.62222 | M29: 144.7371 | N29: 153.6732 | O29: 161.35686
K31: HCP Return
K32: Exit Multiple
J33: =$G$20 -> 134.01584 | K33: 5 | L33: 6 | M33: 7 | N33: 8 | O33: 9
I34: Initial Check | J34: 2 | K34: 107.21267 | L34: 107.21267 | M34: 107.21267 | N34: 107.21267 | O34: 107.21267
J35: 2.2 | K35: 117.93394 | L35: 117.93394 | M35: 117.93394 | N35: 117.93394 | O35: 117.93394
J36: 2.5 | K36: 134.01584 | L36: 134.01584 | M36: 134.01584 | N36: 134.01584 | O36: 134.01584
J37: 2.6 | K37: 139.37647 | L37: 139.37647 | M37: 139.37647 | N37: 139.37647 | O37: 139.37647
J38: 2.7 | K38: 144.7371 | L38: 144.7371 | M38: 144.7371 | N38: 144.7371 | O38: 144.7371
K40: HCP Return
K41: Post-money Valuation
J42: =G20 -> 134.01584 | K42: 20 | L42: 22 | M42: 25 | N42: 28 | O42: 30
I43: Initial Check | J43: 2 | K43: 134.01584 | L43: 121.83258 | M43: 107.21267 | N43: 95.725598 | O43: 89.343891
J44: 2.2 | K44: 147.41742 | L44: 134.01584 | M44: 117.93394 | N44: 105.29816 | O44: 98.27828
J45: 2.5 | K45: 167.5198 | L45: 152.29072 | M45: 134.01584 | N45: 119.657 | O45: 111.67986
J46: 2.6 | K46: 174.22059 | L46: 158.38235 | M46: 139.37647 | N46: 124.44328 | O46: 116.14706
J47: 2.7 | K47: 180.92138 | L47: 164.47398 | M47: 144.7371 | N47: 129.22956 | O47: 120.61425

Sheet TAM Penetration Required
B2: HCP Returns and TAM Analysis
B4: HCP Fund II Size | C4: 134000000
B5: Fund Return | C5: 1
B6: Return Required | C6: =C4*C5 -> 134000000 | G6: Current Market Sizing | U6: 2028 Market Sizing
B8: Target Entry Ownership | C8: ='Exit Scenario'!C10 -> 0.1 | D8: << From exit model
B9: Ownership at Exit | C9: ='Exit Scenario'!G19 -> 0.071145 | D9: << From exit model | G9: @ $50.0k ACV | N9: @ 7.0x exit multiple | U9: @ $6.0k ACV | AB9: @ 8.0x exit multiple
G10: TAM Penetration Required | N10: TAM Penetration Required | U10: TAM Penetration Required | AB10: TAM Penetration Required
B11: ARR Multiple | C11: ='Exit Scenario'!G17 -> 7 | G11: Fund Return | N11: Fund Return | U11: Fund Return | AB11: Fund Return
B12: ARR at Exit Required | C12: =C6/C9/C11 -> 2.690682e+08 | G12: =C18 -> 0.040987772 | H12: 0.5 | I12: 0.75 | J12: 1 | K12: 1.5 | N12: =C18 -> 0.040987772 | O12: 0.5 | P12: 0.75 | Q12: 1 | R12: 1.5 | U12: =C24 -> 0.03332681 | V12: 0.5 | W12: 0.75 | X12: 1 | Y12: 1.5 | AB12: =C24 -> 0.03332681 | AC12: 0.5 | AD12: 0.75 | AE12: 1 | AF12: 1.5
F13: ARR Multiple | G13: =G15-2 -> 5 | H13: 0.02869144 | I13: 0.043037161 | J13: 0.057382881 | K13: 0.086074321 | M13: Wtd Avg ACV | N13: =C14 -> 50000 | O13: 0.020493886 | P13: 0.030740829 | Q13: 0.040987772 | R13: 0.061481658 | T13: ARR Multiple | U13: =U15-2 -> 6 | V13: 0.019440639 | W13: 0.029160958 | X13: 0.038881278 | Y13: 0.058321917 | AA13: Wtd Avg ACV | AB13: =C14 -> 50000 | AC13: 0.016663405 | AD13: 0.024995107 | AE13: 0.03332681 | AF13: 0.049990214
B14: ACV at Exit | C14: 50000 | G14: =G15-1 -> 6 | H14: 0.023909534 | I14: 0.035864301 | J14: 0.047819067 | K14: 0.071728601 | N14: =12*400 -> 4800 | O14: 0.21347798 | P14: 0.32021697 | Q14: 0.42695596 | R14: 0.64043394 | U14: =U15-1 -> 7 | V14: 0.016663405 | W14: 0.024995107 | X14: 0.03332681 | Y14: 0.049990214 | AB14: 30000 | AC14: 0.027772341 | AD14: 0.041658512 | AE14: 0.055544683 | AF14: 0.083317024
B15: Number of Customers Required | C15: =C12/C14 -> 5381.364 | G15: 7 | H15: 0.020493886 | I15: 0.030740829 | J15: 0.040987772 | K15: 0.061481658 | N15: =12*450 -> 5400 | O15: 0.1897582 | P15: 0.28463731 | Q15: 0.37951641 | R15: 0.56927461 | U15: 8 | V15: 0.014580479 | W15: 0.021870719 | X15: 0.029160958 | Y15: 0.043741438 | AB15: =AB14+5000 -> 35000 | AC15: 0.023804864 | AD15: 0.035707296 | AE15: 0.047609728 | AF15: 0.071414592
G16: =G15+1 -> 8 | H16: 0.01793215 | I16: 0.026898225 | J16: 0.035864301 | K16: 0.053796451 | N16: =12*500 -> 6000 | O16: 0.17078238 | P16: 0.25617358 | Q16: 0.34156477 | R16: 0.51234715 | U16: =U15+1 -> 9 | V16: 0.012960426 | W16: 0.019440639 | X16: 0.025920852 | Y16: 0.038881278 | AB16: =AB15+5000 -> 40000 | AC16: 0.020829256 | AD16: 0.031243884 | AE16: 0.041658512 | AF16: 0.062487768
B17: Total Potential Customers | C17: =SUM(TAM!E9:E12) -> 131291.94 | D17: << Market sizing | G17: =G15+2 -> 9 | H17: 0.015939689 | I17: 0.023909534 | J17: 0.031879378 | K17: 0.047819067 | N17: =12*550 -> 6600 | O17: 0.15525671 | P17: 0.23288507 | Q17: 0.31051343 | R17: 0.46577014 | U17: =U15+2 -> 10 | V17: 0.011664383 | W17: 0.017496575 | X17: 0.023328767 | Y17: 0.03499315 | AB17: =AB16+5000 -> 45000 | AC17: 0.018514894 | AD17: 0.027772341 | AE17: 0.037029788 | AF17: 0.055544683
B18: Implied Market Penetration | C18: =C15/C17 -> 0.040987772
B20: Future Outlook | G20: ARR Required ($mm) | N20: ARR Required ($mm)
B21: Total Potential Customers Today | C21: =C17 -> 131291.94 | G21: Fund Return | N21: Fund Return
B22: Annual CAGR | C22: 0.03 | D22: << Market CAGR | G22: =C12 -> 2.690682e+08 | H22: 0.5 | I22: 0.75 | J22: 1 | K22: 1.5 | N22: =C12 -> 2.690682e+08 | O22: 0.5 | P22: 0.75 | Q22: 1 | R22: 1.5
B23: Total Customers in Year 7 | C23: =C21*((C22+1)^7) -> 161472.52 | F23: ARR Multiple | G23: =G25-2 -> 5 | H23: 1.8834774e+08 | I23: 2.8252161e+08 | J23: 3.7669548e+08 | K23: 5.6504322e+08 | M23: Wtd Avg ACV | N23: =C14 -> 50000 | O23: 1.345341e+08 | P23: 2.0180115e+08 | Q23: 2.690682e+08 | R23: 4.036023e+08
B24: Implied Market Penetration in Year 7 | C24: =C15/C23 -> 0.03332681 | G24: =G25-1 -> 6 | H24: 1.5695645e+08 | I24: 2.3543468e+08 | J24: 3.139129e+08 | K24: 4.7086935e+08 | N24: =12*400 -> 4800 | O24: 1.345341e+08 | P24: 2.0180115e+08 | Q24: 2.690682e+08 | R24: 4.036023e+08
G25: 7 | H25: 1.345341e+08 | I25: 2.0180115e+08 | J25: 2.690682e+08 | K25: 4.036023e+08 | N25: =12*450 -> 5400 | O25: 1.345341e+08 | P25: 2.0180115e+08 | Q25: 2.690682e+08 | R25: 4.036023e+08
G26: =G25+1 -> 8 | H26: 1.1771734e+08 | I26: 1.7657601e+08 | J26: 2.3543468e+08 | K26: 3.5315201e+08 | N26: =12*500 -> 6000 | O26: 1.345341e+08 | P26: 2.0180115e+08 | Q26: 2.690682e+08 | R26: 4.036023e+08
G27: =G25+2 -> 9 | H27: 1.0463763e+08 | I27: 1.5695645e+08 | J27: 2.0927527e+08 | K27: 3.139129e+08 | N27: =12*550 -> 6600 | O27: 1.345341e+08 | P27: 2.0180115e+08 | Q27: 2.690682e+08 | R27: 4.036023e+08
G29: # of Customers Implied by ACVs | N29: # of Customers Implied by ACVs
G30: Fund Return | N30: Fund Return
G31: =C15 -> 5381.364 | H31: 0.5 | I31: 0.75 | J31: 1 | K31: 1.5 | N31: =C15 -> 5381.364 | O31: 0.5 | P31: 0.75 | Q31: 1 | R31: 1.5
F32: ARR Multiple | G32: =G34-2 -> 5 | H32: 3766.9548 | I32: 5650.4322 | J32: 7533.9096 | K32: 11300.864 | M32: Wtd Avg ACV | N32: =C14 -> 50000 | O32: 2690.682 | P32: 4036.023 | Q32: 5381.364 | R32: 8072.046
G33: =G34-1 -> 6 | H33: 3139.129 | I33: 4708.6935 | J33: 6278.258 | K33: 9417.387 | N33: =12*400 -> 4800 | O33: 28027.938 | P33: 42041.906 | Q33: 56055.875 | R33: 84083.813
G34: 7 | H34: 2690.682 | I34: 4036.023 | J34: 5381.364 | K34: 8072.046 | N34: =12*450 -> 5400 | O34: 24913.722 | P34: 37370.583 | Q34: 49827.445 | R34: 74741.167
G35: =G34+1 -> 8 | H35: 2354.3468 | I35: 3531.5201 | J35: 4708.6935 | K35: 7063.0403 | N35: =12*500 -> 6000 | O35: 22422.35 | P35: 33633.525 | Q35: 44844.7 | R35: 67267.05
G36: =G34+2 -> 9 | H36: 2092.7527 | I36: 3139.129 | J36: 4185.5053 | K36: 6278.258 | N36: =12*550 -> 6600 | O36: 20383.955 | P36: 30575.932 | Q36: 40767.909 | R36: 61151.864
